setup.cfg
setup.py
backache/__init__.py
backache/antioxidant.py
backache/cache.py
backache/core.py
backache/errors.py
backache/resource.py
backache/utils.py
backache.egg-info/PKG-INFO
backache.egg-info/SOURCES.txt
backache.egg-info/dependency_links.txt
backache.egg-info/entry_points.txt
backache.egg-info/requires.txt
backache.egg-info/top_level.txt
backache.egg-info/zip-safe
tests/__init__.py
tests/celery_utils.py
tests/celery_worker.py
tests/test_bulk.py
tests/test_celery.py
tests/test_mongo.py
tests/test_quarantine.py
tests/test_redirect.py
tests/test_redis.py
tests/test_toupper.py
tests/test_utils.py