Metadata-Version: 1.1
Name: backache
Version: 0.0.6
Summary: Docido software development kit for Python
Home-page: https://github.com/cogniteev/backache
Author: Cogniteev
Author-email: tech@cogniteev.com
License: Apache license version 2.0
Download-URL: https://github.com/cogniteev/backache/archive/v0.0.6.tar.gz
Keywords: cogniteev docido
Platform: UNKNOWN
Classifier: Development Status :: 2 - Pre-Alpha
Classifier: Intended Audience :: Developers
Classifier: License :: OSI Approved :: Apache Software License
Classifier: Topic :: Software Development :: Libraries
Classifier: Topic :: Internet :: WWW/HTTP :: Indexing/Search
Classifier: Programming Language :: Python
Classifier: Programming Language :: Python :: 2.7
Classifier: Operating System :: OS Independent
Classifier: Natural Language :: English
